run_scgsea.py
scgsea_helper.py
scgsea_wrapper.py
scGSEA-1.0.0.dist-info/LICENSE
scGSEA-1.0.0.dist-info/METADATA
scGSEA-1.0.0.dist-info/WHEEL
scGSEA-1.0.0.dist-info/top_level.txt
scGSEA-1.0.0.dist-info/RECORD
