Metadata-Version: 2.1
Name: scGSEA
Version: 1.0.0
Summary: An adaptation of gene set enrichment analysis to clustered single cell data.
Author-email: "Alexander T. Wenzel" <atwenzel@ucsd.edu>
Project-URL: Homepage, https://github.com/genepattern/scGSEA
Project-URL: Issues, https://github.com/genepattern/scGSEA/issues
Classifier: Programming Language :: Python :: 3
Classifier: License :: OSI Approved :: MIT License
Classifier: Operating System :: OS Independent
Requires-Python: >=3.10
License-File: LICENSE
